mulenpay_api/__init__.py
mulenpay_api/payment.py
mulenpay_api/schemas.py
mulenpay_api/subscribe.py
mulenpay_api/abstract/__init__.py
mulenpay_api/abstract/mulenpay_client.py
mulenpay_api/utils/__init__.py
mulenpay_api/utils/calculus.py
mulenpay_api-1.0.11.dist-info/METADATA
mulenpay_api-1.0.11.dist-info/WHEEL
mulenpay_api-1.0.11.dist-info/top_level.txt
mulenpay_api-1.0.11.dist-info/RECORD
