Metadata-Version: 2.1
Name: mulenpay_api
Version: 1.0.11
Summary: Прием платежей и выплаты через Mulen Pay
Author: WALLEXFINTECH
Author-email: platem9@gmail.com
Project-URL: Documentation, https://mulenpay.ru/docs/api
Keywords: payment Mulen Pay wallex
Classifier: Programming Language :: Python :: 3.11
Classifier: License :: OSI Approved :: MIT License
Classifier: Operating System :: OS Independent
Requires-Python: >=3.8
Requires-Dist: pydantic ==2.9.2
Requires-Dist: httpx ==0.27.2
